tests/__init__.py
tests/benchmark_vcf_load.py
tests/common.py
tests/data.py
tests/test_cli_effects.py
tests/test_cli_genes.py
tests/test_collection_filtering.py
tests/test_common.py
tests/test_cosmic_mutations.py
tests/test_dbnsfp_validation.py
tests/test_effect_annotation_errors.py
tests/test_effect_classes.py
tests/test_effect_collection.py
tests/test_effect_collection_serialization.py
tests/test_effects_from_mutagenix_variants.py
tests/test_exonic_splice_site.py
tests/test_frameshift_helpers.py
tests/test_maf.py
tests/test_mm10_klf6_frameshift.py
tests/test_mouse.py
tests/test_mutate.py
tests/test_no_duplicate_variants.py
tests/test_problematic_variants.py
tests/test_reference.py
tests/test_string_helpers.py
tests/test_timings.py
tests/test_variant.py
tests/test_variant_collection.py
tests/test_vcf.py
tests/test_vcf_output.py
varcode/__init__.py
varcode/common.py
varcode/maf.py
varcode/nucleotides.py
varcode/reference.py
varcode/string_helpers.py
varcode/ucsc_reference_names.py
varcode/util.py
varcode/variant.py
varcode/variant_collection.py
varcode/vcf.py
varcode/vcf_output.py
varcode/version.py
varcode/cli/__init__.py
varcode/cli/effects_script.py
varcode/cli/genes_script.py
varcode/cli/logging.conf
varcode/cli/variant_args.py
varcode/cli/version_info.py
varcode/effects/__init__.py
varcode/effects/common.py
varcode/effects/effect_classes.py
varcode/effects/effect_collection.py
varcode/effects/effect_helpers.py
varcode/effects/effect_ordering.py
varcode/effects/effect_prediction.py
varcode/effects/effect_prediction_coding.py
varcode/effects/effect_prediction_coding_frameshift.py
varcode/effects/effect_prediction_coding_in_frame.py
varcode/effects/mutate.py
varcode/effects/transcript_helpers.py
varcode/effects/translate.py
varcode-1.2.1.dist-info/LICENSE
varcode-1.2.1.dist-info/METADATA
varcode-1.2.1.dist-info/WHEEL
varcode-1.2.1.dist-info/entry_points.txt
varcode-1.2.1.dist-info/top_level.txt
varcode-1.2.1.dist-info/RECORD
