Metadata-Version: 2.1
Name: varcode
Version: 1.2.1
Summary: Variant annotation in Python
Home-page: https://github.com/openvax/varcode
Author: Alex Rubinsteyn
Author-email: alex.rubinsteyn@unc.edu
License: http://www.apache.org/licenses/LICENSE-2.0.html
Classifier: Development Status :: 4 - Beta
Classifier: Environment :: Console
Classifier: Operating System :: OS Independent
Classifier: Intended Audience :: Science/Research
Classifier: License :: OSI Approved :: Apache Software License
Classifier: Programming Language :: Python
Classifier: Topic :: Scientific/Engineering :: Bio-Informatics
License-File: LICENSE
Requires-Dist: numpy <2.0,>=1.7
Requires-Dist: pandas >=0.15
Requires-Dist: pyensembl >=1.8.1
Requires-Dist: biopython >=1.64
Requires-Dist: pyvcf3 >=1.0.0
Requires-Dist: memoized-property >=1.0.2
Requires-Dist: serializable >=0.2.1
Requires-Dist: sercol >=0.1.4
